[{"id":1,"subtotal":29540,"total":0,"fechaCreacion":"Fri Jan 27 2023 19:49:21 GMT-0300 (hora est치ndar de Argentina)","products":[{"idProduct":1,"quantity":3},{"idProduct":2,"quantity":1}],"fechaModificacion":"Fri Jan 27 2023 20:54:34 GMT-0300 (hora est치ndar de Argentina)"},{"id":2,"subtotal":0,"total":0,"fechaCreacion":"Fri Jan 27 2023 19:56:41 GMT-0300 (hora est치ndar de Argentina)","products":[]},{"id":3,"subtotal":0,"total":0,"fechaCreacion":"Fri Jan 27 2023 20:18:44 GMT-0300 (hora est치ndar de Argentina)","products":[]}]